parse_pcap/__init__.py
parse_pcap/cli.py
parse_pcap/utils.py
parse_pcap/visualization.py
parse_pcap-0.2.0.dist-info/licenses/LICENSE
parse_pcap-0.2.0.dist-info/METADATA
parse_pcap-0.2.0.dist-info/WHEEL
parse_pcap-0.2.0.dist-info/entry_points.txt
parse_pcap-0.2.0.dist-info/top_level.txt
parse_pcap-0.2.0.dist-info/RECORD
