Metadata-Version: 2.4
Name: parse-pcap
Version: 0.2.0
Summary: A Python package for extracting indicators of compromise (IOCs) from PCAP files.
Author-email: Joshua Bone <jbone.data@gmail.com>
License: GNU GENERAL PUBLIC LICENSE
Project-URL: Homepage, https://github.com/josh-bone/Network-Threat-Detection
Project-URL: Repository, https://github.com/josh-bone/Network-Threat-Detection
Project-URL: Issues, https://github.com/josh-bone/Network-Threat-Detection/issues
Keywords: pcap,ioc,security,network
Requires-Python: >=3.10
License-File: LICENSE
Requires-Dist: pyshark>=0.6
Requires-Dist: requests>=2.32.5
Provides-Extra: test
Requires-Dist: pytest; extra == "test"
Dynamic: license-file
